displayio_cartesian.py
circuitpython_displayio_cartesian-0.5.0.dist-info/licenses/LICENSE
circuitpython_displayio_cartesian-0.5.0.dist-info/METADATA
circuitpython_displayio_cartesian-0.5.0.dist-info/WHEEL
circuitpython_displayio_cartesian-0.5.0.dist-info/top_level.txt
circuitpython_displayio_cartesian-0.5.0.dist-info/RECORD
