Metadata-Version: 2.4
Name: circuitpython-displayio-cartesian
Version: 0.5.0
Summary: A Cartesian plane widget for displaying graphical information.
Author: Jose David M.
License: MIT
Project-URL: Homepage, https://github.com/circuitpython/CircuitPython_DisplayIO_Cartesian
Keywords: adafruit,blinka,circuitpython,micropython,displayio_cartesian,displayio,widget,graphics,gui,graph,chart,graphic
Classifier: Intended Audience :: Developers
Classifier: Topic :: Software Development :: Libraries
Classifier: Topic :: Software Development :: Embedded Systems
Classifier: Topic :: System :: Hardware
Classifier: License :: OSI Approved :: MIT License
Classifier: Programming Language :: Python :: 3
License-File: LICENSE
Requires-Dist: Adafruit-Blinka
Requires-Dist: adafruit-circuitpython-display-text
Requires-Dist: adafruit-circuitpython-displayio-layout
Provides-Extra: optional
Dynamic: license-file
